pytsite/__init__.py
pytsite/__main__.py
pytsite/pytsite.json
pytsite/cache/__init__.py
pytsite/cache/_api.py
pytsite/cache/_driver.py
pytsite/cache/_error.py
pytsite/cache/_pool.py
pytsite/cleanup/__init__.py
pytsite/cleanup/_eh.py
pytsite/console/__init__.py
pytsite/console/_api.py
pytsite/console/_command.py
pytsite/console/_error.py
pytsite/console/_help.py
pytsite/console/_option.py
pytsite/console/res/lang/en.yml
pytsite/console/res/lang/ru.yml
pytsite/console/res/lang/uk.yml
pytsite/cron/__init__.py
pytsite/cron/_api.py
pytsite/cron/_console.py
pytsite/cron/_worker.py
pytsite/cron/res/lang/en.yml
pytsite/cron/res/lang/ru.yml
pytsite/cron/res/lang/uk.yml
pytsite/errors/__init__.py
pytsite/errors/_error.py
pytsite/events/__init__.py
pytsite/formatters/__init__.py
pytsite/formatters/_formatters.py
pytsite/github/__init__.py
pytsite/github/_error.py
pytsite/github/_session.py
pytsite/http/__init__.py
pytsite/http/_error.py
pytsite/http/_headers.py
pytsite/http/_request.py
pytsite/http/_response.py
pytsite/http/_session.py
pytsite/lang/__init__.py
pytsite/lang/_api.py
pytsite/lang/_error.py
pytsite/lang/res/lang/en.yml
pytsite/lang/res/lang/ru.yml
pytsite/lang/res/lang/uk.yml
pytsite/logger/__init__.py
pytsite/logger/_api.py
pytsite/logger/_eh.py
pytsite/mail/__init__.py
pytsite/mail/_api.py
pytsite/mail/_message.py
pytsite/maintenance/__init__.py
pytsite/maintenance/_api.py
pytsite/maintenance/_console_command.py
pytsite/maintenance/res/lang/en.yml
pytsite/maintenance/res/lang/ru.yml
pytsite/maintenance/res/lang/uk.yml
pytsite/metatag/__init__.py
pytsite/metatag/_api.py
pytsite/metatag/res/lang/en.yml
pytsite/metatag/res/lang/ru.yml
pytsite/metatag/res/lang/uk.yml
pytsite/mongodb/__init__.py
pytsite/mongodb/_api.py
pytsite/mongodb/_console_command.py
pytsite/mongodb/res/lang/en.yml
pytsite/mongodb/res/lang/ru.yml
pytsite/mongodb/res/lang/uk.yml
pytsite/package_info/__init__.py
pytsite/package_info/_api.py
pytsite/package_info/_error.py
pytsite/pip/__init__.py
pytsite-9.3.7.dist-info/LICENSE.md
pytsite-9.3.7.dist-info/METADATA
pytsite-9.3.7.dist-info/WHEEL
pytsite-9.3.7.dist-info/top_level.txt
pytsite-9.3.7.dist-info/RECORD
