Metadata-Version: 2.1
Name: pytsite
Version: 9.3.7
Summary: The Rapid Web Application Development Framework
Home-page: https://pytsite.xyz
Author: Oleksandr Shepetko
Author-email: a@shepetko.com
License: MIT
Download-URL: https://github.com/pytsite/pytsite/archive/9.3.7.tar.gz
Platform: UNKNOWN
Classifier: Development Status :: 5 - Production/Stable
Classifier: Environment :: Console
Classifier: Environment :: Web Environment
Classifier: Intended Audience :: Developers
Classifier: License :: OSI Approved :: MIT License
Classifier: Natural Language :: English
Classifier: Natural Language :: Russian
Classifier: Natural Language :: Ukrainian
Classifier: Operating System :: POSIX
Classifier: Programming Language :: Python
Classifier: Programming Language :: Python :: 3.6
Classifier: Programming Language :: Python :: 3.7
Classifier: Programming Language :: Python :: 3.8
Classifier: Programming Language :: JavaScript
Classifier: Topic :: Internet :: WWW/HTTP
Classifier: Topic :: Software Development :: Libraries :: Application Frameworks
Requires-Dist: dateparser (<=0.99999.99999,>=0.7.0)
Requires-Dist: dicmer (<=0.99999.99999,>=0.1.0)
Requires-Dist: frozendict (<=1.99999.99999,>=1.2.0)
Requires-Dist: htmler (<=0.99999.99999,>=0.1.0)
Requires-Dist: htmlmin (<=0.99999.99999,>=0.1.0)
Requires-Dist: jsmin (<=2.99999.99999,>=2.2.0)
Requires-Dist: jinja2 (<=2.99999.99999,>=2.10.0)
Requires-Dist: lxml (<=4.99999.99999,>=4.4.0)
Requires-Dist: pymongo (<=3.99999.99999,>=3.8.0)
Requires-Dist: python-magic (<=0.99999.99999,>=0.4.0)
Requires-Dist: pytz (<=2019.99999.99999,>=2019.1.0)
Requires-Dist: pyyaml (<=5.99999.99999,>=5.1.0)
Requires-Dist: requests (<=2.99999.99999,>=2.22.0)
Requires-Dist: semaver (<=0.99999.99999,>=0.1.0)
Requires-Dist: uwsgi (==2.*)
Requires-Dist: werkzeug (<=0.99999.99999,>=0.15.0)
Requires-Dist: xxhash (<=1.99999.99999,>=1.3.0)
